jupyterlab_retrieve_base_url/__init__.py
jupyterlab_retrieve_base_url/_version.py
jupyterlab_retrieve_base_url-0.1.6.data/data/share/jupyter/labextensions/jupyterlab-retrieve-base-url/package.json
jupyterlab_retrieve_base_url-0.1.6.data/data/share/jupyter/labextensions/jupyterlab-retrieve-base-url/static/728.2fbcaa76be341b9351c6.js
jupyterlab_retrieve_base_url-0.1.6.data/data/share/jupyter/labextensions/jupyterlab-retrieve-base-url/static/821.68d08ce801450a8b7162.js
jupyterlab_retrieve_base_url-0.1.6.data/data/share/jupyter/labextensions/jupyterlab-retrieve-base-url/static/remoteEntry.ad7ba35c8f5403b85833.js
jupyterlab_retrieve_base_url-0.1.6.data/data/share/jupyter/labextensions/jupyterlab-retrieve-base-url/static/style.js
jupyterlab_retrieve_base_url-0.1.6.data/data/share/jupyter/labextensions/jupyterlab-retrieve-base-url/static/third-party-licenses.json
jupyterlab_retrieve_base_url-0.1.6.data/data/share/jupyter/labextensions/jupyterlab-retrieve-base-url/install.json
jupyterlab_retrieve_base_url-0.1.6.dist-info/METADATA
jupyterlab_retrieve_base_url-0.1.6.dist-info/WHEEL
jupyterlab_retrieve_base_url-0.1.6.dist-info/licenses/LICENSE
jupyterlab_retrieve_base_url-0.1.6.dist-info/RECORD
