Metadata-Version: 2.3
Name: jupyterlab_retrieve_base_url
Version: 0.1.6
Summary: A JupyterLab extension to retrieve the base URL from the frontend. It was developped as a workaround for current limitation of `dash` jupyterlab extension that cannot be installed with jupyterlab v4.
Project-URL: Homepage, https://github.com/mthiboust/jupyterlab-retrieve-base-url
Project-URL: Bug Tracker, https://github.com/mthiboust/jupyterlab-retrieve-base-url/issues
Project-URL: Repository, https://github.com/mthiboust/jupyterlab-retrieve-base-url.git
Author: Matthieu Thiboust
License: BSD 3-Clause License
License-File: LICENSE
Keywords: jupyter,jupyterlab,jupyterlab-extension
Classifier: Framework :: Jupyter
Classifier: Framework :: Jupyter :: JupyterLab
Classifier: Framework :: Jupyter :: JupyterLab :: 4
Classifier: Framework :: Jupyter :: JupyterLab :: Extensions
Classifier: Framework :: Jupyter :: JupyterLab :: Extensions :: Prebuilt
Classifier: License :: OSI Approved :: BSD License
Classifier: Programming Language :: Python
Classifier: Programming Language :: Python :: 3
Classifier: Programming Language :: Python :: 3.8
Classifier: Programming Language :: Python :: 3.9
Classifier: Programming Language :: Python :: 3.10
Classifier: Programming Language :: Python :: 3.11
Classifier: Programming Language :: Python :: 3.12
Requires-Python: >=3.8
